zather/__init__.py
zather/agent.py
zather/cli.py
zather/environment.py
zather/prompting.py
zather/trajectory.py
zather/utils.py
zather/prompts/path_pack.yaml
zather/sources/__init__.py
zather/sources/claude_code.py
zather/sources/codex_cli.py
zather-0.3.0.dist-info/METADATA
zather-0.3.0.dist-info/WHEEL
zather-0.3.0.dist-info/entry_points.txt
zather-0.3.0.dist-info/RECORD
