Metadata-Version: 2.4
Name: zather
Version: 0.3.0
Summary: Zubin Pather - generate zethis-style Path Packs from agent session logs
Requires-Python: >=3.13
Requires-Dist: anthropic>=0.75.0
Requires-Dist: openai>=1.0.0
Requires-Dist: pyyaml>=6.0
Requires-Dist: wbal>=0.3.2
Requires-Dist: weave>=0.51.0
Provides-Extra: dev
Requires-Dist: pytest>=8.0; extra == 'dev'
